{"sections":[{"anchor":"h2-桓公元年-be34b0","children":[],"end":93,"level":2,"start":19,"title":"桓公元年"},{"anchor":"h2-桓公二年-5886ae","children":[],"end":225,"level":2,"start":93,"title":"桓公二年"},{"anchor":"h2-桓公三年-2d4497","children":[],"end":347,"level":2,"start":225,"title":"桓公三年"},{"anchor":"h2-桓公四年-c2fe0e","children":[],"end":384,"level":2,"start":347,"title":"桓公四年"},{"anchor":"h2-桓公五年-f43439","children":[],"end":484,"level":2,"start":384,"title":"桓公五年"},{"anchor":"h2-桓公六年-129616","children":[],"end":559,"level":2,"start":484,"title":"桓公六年"},{"anchor":"h2-桓公七年-334854","children":[],"end":600,"level":2,"start":559,"title":"桓公七年"},{"anchor":"h2-桓公八年-7cee96","children":[],"end":674,"level":2,"start":600,"title":"桓公八年"},{"anchor":"h2-桓公九年-b83fb7","children":[],"end":726,"level":2,"start":674,"title":"桓公九年"},{"anchor":"h2-桓公十年-7e90cb","children":[],"end":804,"level":2,"start":726,"title":"桓公十年"},{"anchor":"h2-桓公十一年-bb61ab","children":[],"end":1193,"level":2,"start":804,"title":"桓公十一年"},{"anchor":"h2-桓公十二年-bde64f","children":[],"end":1337,"level":2,"start":1193,"title":"桓公十二年"},{"anchor":"h2-桓公十三年-1187b9","children":[],"end":1428,"level":2,"start":1337,"title":"桓公十三年"},{"anchor":"h2-桓公十四年-9c54a7","children":[],"end":1532,"level":2,"start":1428,"title":"桓公十四年"},{"anchor":"h2-桓公十五年-43b8e1","children":[],"end":1679,"level":2,"start":1532,"title":"桓公十五年"},{"anchor":"h2-桓公十六年-f726d2","children":[],"end":1768,"level":2,"start":1679,"title":"桓公十六年"},{"anchor":"h2-桓公十七年-861f98","children":[],"end":1892,"level":2,"start":1768,"title":"桓公十七年"},{"anchor":"h2-桓公十八年-882575","children":[],"end":2000,"level":2,"start":1892,"title":"桓公十八年"}],"slug":"wikisource-春秋公羊傳-桓公"}