{"sections":[{"anchor":"h2-上德與下德之辨-cbcf4c","children":[],"end":225,"level":2,"start":46,"title":"上德與下德之辨"},{"anchor":"h2-德之四等-9977bb","children":[],"end":558,"level":2,"start":225,"title":"德之四等"},{"anchor":"h2-失道而後德之序-0ba8b1","children":[],"end":767,"level":2,"start":558,"title":"失道而後德之序"},{"anchor":"h2-前識之蔽-b188d9","children":[],"end":885,"level":2,"start":767,"title":"前識之蔽"},{"anchor":"h2-大丈夫之取捨-dd66c4","children":[],"end":1046,"level":2,"start":885,"title":"大丈夫之取捨"},{"anchor":"h2-總結-2ab09a","children":[],"end":1134,"level":2,"start":1046,"title":"總結"}],"slug":"dao-de-jing-di-san-shi-ba-zhang","status":"ok","title":"道德經第三十八章義疏"}