{"sections":[{"anchor":"h2-禹-ca327a","children":[],"end":3033,"level":2,"start":18,"title":"禹"},{"anchor":"h2-啓-a729af","children":[],"end":3175,"level":2,"start":3033,"title":"啓"},{"anchor":"h2-太康-30ef88","children":[],"end":3202,"level":2,"start":3175,"title":"太康"},{"anchor":"h2-中康-dbaf67","children":[],"end":3236,"level":2,"start":3202,"title":"中康"},{"anchor":"h2-相至孔甲-ce2655","children":[],"end":3383,"level":2,"start":3236,"title":"相至孔甲"},{"anchor":"h2-皋至桀-bfa3c5","children":[],"end":3507,"level":2,"start":3383,"title":"皋至桀"},{"anchor":"h2-太史公論-5f780f","children":[],"end":3592,"level":2,"start":3507,"title":"太史公論"},{"anchor":"h2-校勘記-ef4d09","children":[],"end":3598,"level":2,"start":3592,"title":"校勘記"}],"slug":"wikisource-史記-卷002"}