{"backlinks":[{"slug":"端言直道","title":"端言直道"}],"content":"明劫者，姦臣竊國之第一途。其狀云何？羣臣持祿以養交，行私道而不效公忠。\n\n夫國有賢良，逆者必有禍，順者必有福；彼則逆亦不敢言，順亦不為忠，但知持祿待時、交結攀援而已。國家有事，彼皆袖手旁觀，無有挺身效命者。君以為臣滿朝，實則國無一人。\n\n明者何？此輩姦狀明白，人皆可見，而君或不知，故曰明。非隱微之姦，乃昭然之害也。[[三劫]]之一。\n\n**所出**：《韓非子 · 三守》 — https://zh.wikisource.org/wiki/韓非子/三守","slug":"明劫","sources":[{"chapter":"三守","plugin":"wikisource","title":"韓非子 · 三守","url":"https://zh.wikisource.org/wiki/韓非子/三守","work":"韓非子"}],"status":"ok","summary":"羣臣持祿養交、行私廢公之姦，此姦之大者也。","tags":["韓非","朋黨","法家","姦臣","部:子","部:子/法家類"],"title":"明劫"}