{"backlinks":[{"slug":"縣火防守","title":"縣火防守"},{"slug":"雲梯攻城","title":"雲梯攻城"},{"slug":"突門","title":"突門"}],"content":"**行城襍樓**為墨子城守術之核心構造。「行城」者，可移動之城牆也；「襍樓」者，多層之防守塔也。墨子云：「守為行城，襍樓相見，以環其中，以適廣陜為度，環中藉幕，毋廣其處。」\n\n行城之制，「高城二十尺，上加堞，廣十尺，左右出巨各二十尺，高廣如行城之法」。此城牆高二十尺，上有女牆，寬十尺，兩側各突出巨木結構二十尺。城上設爵穴、煇𠏙等箭孔，置機、衝、錢、城等攻守器械，選精壯之士十人持鎸、劍，五人持衝以備敵。此複合式防禦體系，以外圍之行城阻敵鋒銳，主城居中，形成層層設防之勢。敵攻行城，則主城可出援；敵越行城，則腹背受敵。此與[[守圍城之法]]相參，構成墨家完整之城守體系。","slug":"行城襍樓","sources":[{"chapter":"備梯","plugin":"wikisource","title":"墨子 · 備梯","url":"https://zh.wikisource.org/wiki/墨子/備梯","work":"墨子"}],"status":"ok","summary":"行城襍樓是墨子城守术中由可移动的“行城”与多层防御塔“襍樓”组成的复合防御体系，以外围行城阻挡敌人、主城居中互援，实现层层设防。","tags":["墨家","防禦術","城防建築","器械","兵法","部:子","部:子/墨家類"],"title":"行城襍樓"}