{"sections":[{"anchor":"h2-序-2722ec","children":[],"end":69,"level":2,"start":0,"title":"序"},{"anchor":"h2-孫叔敖-1cccb9","children":[],"end":500,"level":2,"start":69,"title":"孫叔敖"},{"anchor":"h2-子産-362abe","children":[],"end":663,"level":2,"start":500,"title":"子産"},{"anchor":"h2-公儀休-b4e9c8","children":[],"end":858,"level":2,"start":663,"title":"公儀休"},{"anchor":"h2-石奢-f291e2","children":[],"end":1035,"level":2,"start":858,"title":"石奢"},{"anchor":"h2-李離-e8a472","children":[],"end":1234,"level":2,"start":1035,"title":"李離"},{"anchor":"h2-太史公曰-56883d","children":[],"end":1311,"level":2,"start":1234,"title":"太史公曰"}],"slug":"wikisource-史記-卷119"}