{"sections":[{"anchor":"h2-僖公元年-f0c9d2","children":[],"end":788,"level":2,"start":19,"title":"僖公元年"},{"anchor":"h2-僖公二年-ad3c26","children":[],"end":1641,"level":2,"start":788,"title":"僖公二年"},{"anchor":"h2-僖公三年-690bbe","children":[],"end":1817,"level":2,"start":1641,"title":"僖公三年"},{"anchor":"h2-僖公四年-a7a2e2","children":[],"end":2393,"level":2,"start":1817,"title":"僖公四年"},{"anchor":"h2-僖公五年-61dec5","children":[],"end":2694,"level":2,"start":2393,"title":"僖公五年"},{"anchor":"h2-僖公六年-51c00d","children":[],"end":2779,"level":2,"start":2694,"title":"僖公六年"},{"anchor":"h2-僖公七年-1551fb","children":[],"end":2893,"level":2,"start":2779,"title":"僖公七年"},{"anchor":"h2-僖公八年-b87123","children":[],"end":3119,"level":2,"start":2893,"title":"僖公八年"},{"anchor":"h2-僖公九年-cc3668","children":[],"end":3400,"level":2,"start":3119,"title":"僖公九年"},{"anchor":"h2-僖公十年-12315e","children":[],"end":3988,"level":2,"start":3400,"title":"僖公十年"},{"anchor":"h2-僖公十一年-9083e0","children":[],"end":4051,"level":2,"start":3988,"title":"僖公十一年"},{"anchor":"h2-僖公十二年-808cc8","children":[],"end":4113,"level":2,"start":4051,"title":"僖公十二年"},{"anchor":"h2-僖公十三年-69d01b","children":[],"end":4192,"level":2,"start":4113,"title":"僖公十三年"},{"anchor":"h2-僖公十四年-10da57","children":[],"end":4532,"level":2,"start":4192,"title":"僖公十四年"},{"anchor":"h2-僖公十五年-6a823a","children":[],"end":4833,"level":2,"start":4532,"title":"僖公十五年"},{"anchor":"h2-僖公十六年-b2e728","children":[],"end":5113,"level":2,"start":4833,"title":"僖公十六年"},{"anchor":"h2-僖公十七年-0592fe","children":[],"end":5261,"level":2,"start":5113,"title":"僖公十七年"},{"anchor":"h2-僖公十八年-c6cfbd","children":[],"end":5441,"level":2,"start":5261,"title":"僖公十八年"},{"anchor":"h2-僖公十九年-8962a2","children":[],"end":5618,"level":2,"start":5441,"title":"僖公十九年"},{"anchor":"h2-僖公廿年-0cda43","children":[],"end":5786,"level":2,"start":5618,"title":"僖公廿年"},{"anchor":"h2-僖公廿一年-d47280","children":[],"end":6314,"level":2,"start":5786,"title":"僖公廿一年"},{"anchor":"h2-僖公廿二年-e7f3f5","children":[],"end":6606,"level":2,"start":6314,"title":"僖公廿二年"},{"anchor":"h2-僖公廿三年-0718e8","children":[],"end":6696,"level":2,"start":6606,"title":"僖公廿三年"},{"anchor":"h2-僖公廿四年-4a0c73","children":[],"end":6793,"level":2,"start":6696,"title":"僖公廿四年"},{"anchor":"h2-僖公廿五年-43da5b","children":[],"end":6983,"level":2,"start":6793,"title":"僖公廿五年"},{"anchor":"h2-僖公廿六年-e58e7f","children":[],"end":7215,"level":2,"start":6983,"title":"僖公廿六年"},{"anchor":"h2-僖公廿七年-fe1194","children":[],"end":7348,"level":2,"start":7215,"title":"僖公廿七年"},{"anchor":"h2-僖公廿八年-ee5ca1","children":[],"end":8294,"level":2,"start":7348,"title":"僖公廿八年"},{"anchor":"h2-僖公廿九年-61c1e4","children":[],"end":8402,"level":2,"start":8294,"title":"僖公廿九年"},{"anchor":"h2-僖公卅年-df60d5","children":[],"end":8584,"level":2,"start":8402,"title":"僖公卅年"},{"anchor":"h2-僖公卅一年-7afad5","children":[],"end":9044,"level":2,"start":8584,"title":"僖公卅一年"},{"anchor":"h2-僖公卅二年-f80361","children":[],"end":9115,"level":2,"start":9044,"title":"僖公卅二年"},{"anchor":"h2-僖公卅三年-0c987d","children":[],"end":9621,"level":2,"start":9115,"title":"僖公卅三年"}],"slug":"wikisource-春秋公羊傳-僖公"}