{"sections":[{"anchor":"h2-衞康叔-8bd9ac","children":[],"end":423,"level":2,"start":0,"title":"衞康叔"},{"anchor":"h2-衞頃侯-6b2cca","children":[],"end":461,"level":2,"start":423,"title":"衞頃侯"},{"anchor":"h2-衞釐侯-ba74e8","children":[],"end":519,"level":2,"start":461,"title":"衞釐侯"},{"anchor":"h2-衞共伯-9781b2","children":[],"end":595,"level":2,"start":519,"title":"衞共伯"},{"anchor":"h2-衞武公-342e09","children":[],"end":669,"level":2,"start":595,"title":"衞武公"},{"anchor":"h2-衞莊公-a88a4d","children":[],"end":819,"level":2,"start":669,"title":"衞莊公"},{"anchor":"h2-衞桓公-cc2f0e","children":[],"end":1011,"level":2,"start":819,"title":"衞桓公"},{"anchor":"h2-衞宣公-efe3c5","children":[],"end":1417,"level":2,"start":1011,"title":"衞宣公"},{"anchor":"h2-衞惠公-5bcbcc","children":[],"end":1641,"level":2,"start":1417,"title":"衞惠公"},{"anchor":"h2-衞懿公-ba1046","children":[],"end":1713,"level":2,"start":1641,"title":"衞懿公"},{"anchor":"h2-衞戴公-bf2cb5","children":[],"end":1800,"level":2,"start":1713,"title":"衞戴公"},{"anchor":"h2-衞文公-9401d5","children":[],"end":2057,"level":2,"start":1800,"title":"衞文公"},{"anchor":"h2-衞成公-4925f6","children":[],"end":2282,"level":2,"start":2057,"title":"衞成公"},{"anchor":"h2-衞穆公-b7ff4f","children":[],"end":2376,"level":2,"start":2282,"title":"衞穆公"},{"anchor":"h2-衞獻公殤公-0e900c","children":[],"end":2827,"level":2,"start":2376,"title":"衞獻公、殤公"},{"anchor":"h2-衞襄公-c6f7ff","children":[],"end":2978,"level":2,"start":2827,"title":"衞襄公"},{"anchor":"h2-衞靈公-5fedbf","children":[],"end":3133,"level":2,"start":2978,"title":"衞靈公"},{"anchor":"h2-衞出公-9b4b69","children":[],"end":3800,"level":2,"start":3133,"title":"衞出公"},{"anchor":"h2-衞莊公-a88a4d-2","children":[],"end":3960,"level":2,"start":3800,"title":"衞莊公"},{"anchor":"h2-衞君起-cd76fb","children":[],"end":4065,"level":2,"start":3960,"title":"衞君起"},{"anchor":"h2-衞悼公-d15cd7","children":[],"end":4087,"level":2,"start":4065,"title":"衞悼公"},{"anchor":"h2-衞敬公-011030","children":[],"end":4110,"level":2,"start":4087,"title":"衞敬公"},{"anchor":"h2-衞昭公-955c5f","children":[],"end":4152,"level":2,"start":4110,"title":"衞昭公"},{"anchor":"h2-衞懷公-7c0512","children":[],"end":4183,"level":2,"start":4152,"title":"衞懷公"},{"anchor":"h2-衞愼公-a0b88c","children":[],"end":4222,"level":2,"start":4183,"title":"衞愼公"},{"anchor":"h2-衞聲公-556b72","children":[],"end":4245,"level":2,"start":4222,"title":"衞聲公"},{"anchor":"h2-衞成侯-9d4d54","children":[],"end":4294,"level":2,"start":4245,"title":"衞成侯"},{"anchor":"h2-衞平侯-cabc40","children":[],"end":4315,"level":2,"start":4294,"title":"衞平侯"},{"anchor":"h2-衞嗣君-beb340","children":[],"end":4352,"level":2,"start":4315,"title":"衞嗣君"},{"anchor":"h2-衞懷君-883538","children":[],"end":4390,"level":2,"start":4352,"title":"衞懷君"},{"anchor":"h2-衞元君-1bf070","children":[],"end":4458,"level":2,"start":4390,"title":"衞元君"},{"anchor":"h2-衞君角-ddbb12","children":[],"end":4502,"level":2,"start":4458,"title":"衞君角"},{"anchor":"h2-太史公曰-56883d","children":[],"end":4597,"level":2,"start":4502,"title":"太史公曰"},{"anchor":"h2-索隱述贊-12da7b","children":[],"end":4687,"level":2,"start":4597,"title":"索隱述贊"}],"slug":"wikisource-史記-卷037"}