{"chapter":"常武","content":"召穆公美宣王也。有常德以立武事，因以為戒然。」\n\n### 常武\n:赫赫明明，王命卿士。南仲大祖，大師皇父，\n:整我六師，以脩我戎。既敬既戒，惠此南國。\n\n:王謂尹氏，命程伯休父，左右陳行，戒我師旅。\n:率彼淮浦，省此徐土。不留不處，三事就緒。\n\n:赫赫業業，有嚴天子。王舒保作，匪紹匪遊。\n:徐方繹騷，震驚徐方。如雷如霆，徐方震驚。\n\n:王奮厥武，如震如怒。進厥虎臣，闞如虓虎。\n:鋪敦淮濆，仍執醜虜。截彼淮浦，王師之所。\n\n:王旅嘽嘽，如飛如翰，如江如漢。如山之苞，如川之流。\n:緜緜翼翼，不測不克，濯征徐國。\n\n:王猶允塞，徐方既來。徐方既同，天子之功。\n:四方既平，徐方來庭。徐方不回，王曰還歸。\n\n:《常武》，六章，章八句。\n\n### 註解\n\n__NOTOC__\n__NOEDITSECTION__","next":{"chapter":"干旄","slug":"wikisource-詩經-干旄"},"prev":{"chapter":"常棣","slug":"wikisource-詩經-常棣"},"slug":"wikisource-詩經-常武","source_url":"https://zh.wikisource.org/wiki/詩經/常武","title":"詩經 · 常武","work":"詩經"}