{"chapter":"臨","content":"周易　第十九卦\n\n;臨\nalt=䷒ 兌下坤上\n\n***易經：**\n****臨**：元亨。利貞。至-{于}-八月有凶。\n*#初九：咸臨，貞吉。\n*#九二：咸臨，吉-{無}-不利。\n*#六三：甘臨，-{無}-攸利。既憂之，-{無}-咎。\n*#六四：至臨，-{無}-咎。\n*#六五：知臨，大君之宜，吉。\n*#上六：敦臨，吉-{無}-咎。\n\n***彖曰：**\n**臨，剛浸而長。說而順，剛中而應，大亨以正，天之道也。至-{于}-八月有凶，消不久也。\n\n***象曰：**\n**澤上有地，臨；君子以教思-{無}-窮，容保民-{無}-疆。\n*#咸臨貞吉，志行正也。\n*#咸臨，吉-{無}-不利；未順命也。\n*#甘臨，位不當也。既憂之，咎不長也。\n*#至臨-{無}-咎，位當也。\n*#大君之宜，行中之謂也。\n*#敦臨之吉，志在內也。","next":{"chapter":"艮","slug":"wikisource-周易-艮"},"prev":{"chapter":"節","slug":"wikisource-周易-節"},"slug":"wikisource-周易-臨","source_url":"https://zh.wikisource.org/wiki/周易/臨","title":"周易 · 臨","work":"周易"}