{"sections":[{"anchor":"h2-玄要篇上-74c446","children":[{"anchor":"h3-倣古二章-d83e93","children":[{"anchor":"h4-又-df331c","children":[],"end":444,"level":4,"start":290,"title":"又"}],"end":444,"level":3,"start":134,"title":"倣古二章"},{"anchor":"h3-上天梯-097e8d","children":[],"end":742,"level":3,"start":444,"title":"上天梯"},{"anchor":"h3-親口訣-850c6b","children":[],"end":895,"level":3,"start":742,"title":"親口訣"},{"anchor":"h3-答永樂皇帝-432574","children":[],"end":992,"level":3,"start":895,"title":"答永樂皇帝"},{"anchor":"h3-道情歌-28204a","children":[],"end":1423,"level":3,"start":992,"title":"道情歌"},{"anchor":"h3-煉鉛歌-30d410","children":[],"end":1654,"level":3,"start":1423,"title":"煉鉛歌"},{"anchor":"h3-先天炁一歌-b7be10","children":[],"end":1785,"level":3,"start":1654,"title":"先天炁一歌"},{"anchor":"h3-鉛火歌-3f23af","children":[],"end":1999,"level":3,"start":1785,"title":"鉛火歌"},{"anchor":"h3-了道歌-885605","children":[],"end":2273,"level":3,"start":1999,"title":"了道歌"},{"anchor":"h3-打坐歌-46cd5d","children":[],"end":2793,"level":3,"start":2273,"title":"打坐歌"},{"anchor":"h3-道要祕訣歌-824220","children":[],"end":3196,"level":3,"start":2793,"title":"道要祕訣歌"},{"anchor":"h3-大道歌-922496","children":[],"end":4268,"level":3,"start":3196,"title":"大道歌"},{"anchor":"h3-眞槖籥歌-9df848","children":[],"end":4381,"level":3,"start":4268,"title":"眞槖籥歌"},{"anchor":"h3-玄關一竅歌-5f87a4","children":[],"end":4495,"level":3,"start":4381,"title":"玄關一竅歌"},{"anchor":"h3-煉鉛歌-30d410-2","children":[],"end":4777,"level":3,"start":4495,"title":"煉鉛歌"},{"anchor":"h3-金丹歌-63289d","children":[],"end":5195,"level":3,"start":4777,"title":"金丹歌"},{"anchor":"h3-金液還丹破迷歌-21e488","children":[],"end":6113,"level":3,"start":5195,"title":"金液還丹破迷歌"},{"anchor":"h3-龍虎還丹指迷歌-4ff3c9","children":[{"anchor":"h4-又-1e9af9","children":[],"end":6459,"level":4,"start":6280,"title":"又"}],"end":6459,"level":3,"start":6113,"title":"龍虎還丹指迷歌"},{"anchor":"h3-註九皇丹經三月生魂金丹三還一返歌-5f82e3","children":[],"end":6638,"level":3,"start":6459,"title":"註九皇丹經三月生魂金丹三還一返歌"},{"anchor":"h3-註九皇丹經四月生魄金丹四還二返歌-09dfbc","children":[],"end":6755,"level":3,"start":6638,"title":"註九皇丹經四月生魄金丹四還二返歌"},{"anchor":"h3-註九皇丹經七月開心七竅金丹七還五返歌-2da47d","children":[],"end":6869,"level":3,"start":6755,"title":"註九皇丹經七月開心七竅金丹七還五返歌"},{"anchor":"h3-註九皇丹經十月形神堅固金丹十還歌-429f72","children":[],"end":7068,"level":3,"start":6869,"title":"註九皇丹經十月形神堅固金丹十還歌"},{"anchor":"h3-固漏歌-0675e0","children":[],"end":7418,"level":3,"start":7068,"title":"固漏歌"},{"anchor":"h3-了道歌-885605-2","children":[],"end":7676,"level":3,"start":7418,"title":"了道歌"},{"anchor":"h3-迴文詩-08c260","children":[],"end":7754,"level":3,"start":7676,"title":"迴文詩"},{"anchor":"h3-金丹詩三十六首-caf420","children":[{"anchor":"h4-養道皈眞-0ece02","children":[],"end":7847,"level":4,"start":7767,"title":"養道皈眞"},{"anchor":"h4-離塵歸隱-43c55c","children":[],"end":7927,"level":4,"start":7847,"title":"離塵歸隱"},{"anchor":"h4-掃境修心-9a64cb","children":[],"end":8007,"level":4,"start":7927,"title":"掃境修心"},{"anchor":"h4-力敵睡魔-971eb5","children":[],"end":8087,"level":4,"start":8007,"title":"力敵睡魔"},{"anchor":"h4-一求玄關-333026","children":[],"end":8167,"level":4,"start":8087,"title":"一求玄關"},{"anchor":"h4-再求玄關-16b850","children":[],"end":8247,"level":4,"start":8167,"title":"再求玄關"},{"anchor":"h4-總論玄關-109bf5","children":[],"end":8327,"level":4,"start":8247,"title":"總論玄關"},{"anchor":"h4-鎔鑄神劍-6590a9","children":[],"end":8407,"level":4,"start":8327,"title":"鎔鑄神劍"},{"anchor":"h4-後天築基-452408","children":[],"end":8487,"level":4,"start":8407,"title":"後天築基"},{"anchor":"h4-後天煉已-689a0f","children":[],"end":8567,"level":4,"start":8487,"title":"後天煉已"},{"anchor":"h4-煉已得藥-d39055","children":[],"end":8647,"level":4,"start":8567,"title":"煉已得藥"},{"anchor":"h4-煉已下手-3d0279","children":[],"end":8727,"level":4,"start":8647,"title":"煉已下手"},{"anchor":"h4-先天鼎器-9838e7","children":[],"end":8807,"level":4,"start":8727,"title":"先天鼎器"},{"anchor":"h4-先天眞鉛-dd5603","children":[],"end":8887,"level":4,"start":8807,"title":"先天眞鉛"},{"anchor":"h4-先天大藥-0c83fa","children":[],"end":8967,"level":4,"start":8887,"title":"先天大藥"},{"anchor":"h4-擒捉先天-64beb2","children":[],"end":9047,"level":4,"start":8967,"title":"擒捉先天"},{"anchor":"h4-凝聚先天-3c64e0","children":[],"end":9127,"level":4,"start":9047,"title":"凝聚先天"},{"anchor":"h4-認藥採取-494219","children":[],"end":9207,"level":4,"start":9127,"title":"認藥採取"},{"anchor":"h4-直指眞鉛-499fbb","children":[],"end":9287,"level":4,"start":9207,"title":"直指眞鉛"},{"anchor":"h4-直指眞汞-fa9cd1","children":[],"end":9367,"level":4,"start":9287,"title":"直指眞汞"},{"anchor":"h4-鉛汞相投-7daa9c","children":[],"end":9447,"level":4,"start":9367,"title":"鉛汞相投"},{"anchor":"h4-顚倒妙用-d34ea7","children":[],"end":9527,"level":4,"start":9447,"title":"顚倒妙用"},{"anchor":"h4-和合丹頭-ff26d8","children":[],"end":9607,"level":4,"start":9527,"title":"和合丹頭"},{"anchor":"h4-三家相見-39f916","children":[],"end":9687,"level":4,"start":9607,"title":"三家相見"},{"anchor":"h4-九轉大還-6a4975","children":[],"end":9767,"level":4,"start":9687,"title":"九轉大還"},{"anchor":"h4-火候細微-eb1c5d","children":[],"end":9847,"level":4,"start":9767,"title":"火候細微"},{"anchor":"h4-脫胎神化-51639b","children":[],"end":9927,"level":4,"start":9847,"title":"脫胎神化"},{"anchor":"h4-面壁九年-e9b8ea","children":[],"end":10007,"level":4,"start":9927,"title":"面壁九年"},{"anchor":"h4-換鼎分胎-8f55af","children":[],"end":10087,"level":4,"start":10007,"title":"換鼎分胎"},{"anchor":"h4-轉制通靈-04c517","children":[],"end":10167,"level":4,"start":10087,"title":"轉制通靈"},{"anchor":"h4-九轉靈變-1deece","children":[],"end":10247,"level":4,"start":10167,"title":"九轉靈變"},{"anchor":"h4-修煉天元-e3d45a","children":[],"end":10327,"level":4,"start":10247,"title":"修煉天元"},{"anchor":"h4-瀟洒優游-27a35b","children":[],"end":10407,"level":4,"start":10327,"title":"瀟洒優游"},{"anchor":"h4-了道度人-bb7f27","children":[],"end":10487,"level":4,"start":10407,"title":"了道度人"},{"anchor":"h4-總詠内事-1288ca","children":[],"end":10567,"level":4,"start":10487,"title":"總詠内事"},{"anchor":"h4-總詠外事-7937ce","children":[],"end":10647,"level":4,"start":10567,"title":"總詠外事"},{"anchor":"h4-詠先天鼎-1d99fa","children":[],"end":10711,"level":4,"start":10647,"title":"詠先天鼎"}],"end":10711,"level":3,"start":7754,"title":"金丹詩三十六首"},{"anchor":"h3-金丹詩二十四首-7db3d1","children":[],"end":12384,"level":3,"start":10711,"title":"金丹詩二十四首"},{"anchor":"h3-大丹詩八首書武當道室示諸弟子-e36759","children":[],"end":12956,"level":3,"start":12384,"title":"大丹詩八首書武當道室示諸弟子"},{"anchor":"h3-瓊花詩-80694b","children":[],"end":13034,"level":3,"start":12956,"title":"瓊花詩"},{"anchor":"h3-七絕-8973fd","children":[{"anchor":"h4-又-87e232","children":[],"end":13120,"level":4,"start":13077,"title":"又"},{"anchor":"h4-又-87e232-2","children":[],"end":13163,"level":4,"start":13120,"title":"又"},{"anchor":"h4-又-87e232-3","children":[],"end":13206,"level":4,"start":13163,"title":"又"},{"anchor":"h4-又-87e232-4","children":[],"end":13374,"level":4,"start":13206,"title":"又"}],"end":13374,"level":3,"start":13034,"title":"七絕"}],"end":13374,"level":2,"start":125,"title":"玄要篇上"},{"anchor":"h2-玄要篇下-f9072c","children":[{"anchor":"h3-登高臺-d603e1","children":[],"end":13991,"level":3,"start":13383,"title":"登高臺"},{"anchor":"h3-天仙引-2bcdfe","children":[{"anchor":"h4-第二體-a5dacf","children":[],"end":14482,"level":4,"start":14238,"title":"第二體"},{"anchor":"h4-第三體-e5e26b","children":[],"end":14740,"level":4,"start":14482,"title":"第三體"},{"anchor":"h4-第四體-a03259","children":[],"end":14976,"level":4,"start":14740,"title":"第四體"},{"anchor":"h4-第五體-f8e5fc","children":[],"end":15533,"level":4,"start":14976,"title":"第五體"}],"end":15533,"level":3,"start":13991,"title":"天仙引"},{"anchor":"h3-一枝花-295f0e","children":[{"anchor":"h4-第一-2d6720","children":[],"end":16093,"level":4,"start":15794,"title":"第一"},{"anchor":"h4-第三-cbd9cd","children":[],"end":16324,"level":4,"start":16093,"title":"第三"},{"anchor":"h4-第四-b271cf","children":[],"end":16559,"level":4,"start":16324,"title":"第四"}],"end":16559,"level":3,"start":15533,"title":"一枝花"},{"anchor":"h3-詠蟄龍法-ec4d4d","children":[{"anchor":"h4-漁父詞-ef0b3d","children":[],"end":16613,"level":4,"start":16569,"title":"漁父詞"},{"anchor":"h4-蟄龍吟-039245","children":[],"end":16824,"level":4,"start":16613,"title":"蟄龍吟"}],"end":16824,"level":3,"start":16559,"title":"詠蟄龍法"},{"anchor":"h3-美金華二首-c2a664","children":[],"end":17251,"level":3,"start":16824,"title":"美金華二首"},{"anchor":"h3-一訣天機-5835e8","children":[],"end":17345,"level":3,"start":17251,"title":"一訣天機"},{"anchor":"h3-玄關交媾曲-d7b2de","children":[],"end":17418,"level":3,"start":17345,"title":"玄關交媾曲"},{"anchor":"h3-陰陽交會曲-bec43c","children":[],"end":17533,"level":3,"start":17418,"title":"陰陽交會曲"},{"anchor":"h3-洞天淸唱六曡-b1543f","children":[{"anchor":"h4-一曡-702dc6","children":[],"end":17652,"level":4,"start":17545,"title":"一曡"},{"anchor":"h4-二曡-4087d3","children":[],"end":17767,"level":4,"start":17652,"title":"二曡"},{"anchor":"h4-三曡-5b2653","children":[],"end":17852,"level":4,"start":17767,"title":"三曡"},{"anchor":"h4-四曡-a8ac29","children":[],"end":17958,"level":4,"start":17852,"title":"四曡"},{"anchor":"h4-五曡-870cfd","children":[],"end":18051,"level":4,"start":17958,"title":"五曡"},{"anchor":"h4-六曡-5aea84","children":[],"end":18090,"level":4,"start":18051,"title":"六曡"}],"end":18090,"level":3,"start":17533,"title":"洞天淸唱六曡"},{"anchor":"h3-麗春院詞二首-8f57bf","children":[{"anchor":"h4-又-6dd893","children":[],"end":18234,"level":4,"start":18164,"title":"又"}],"end":18234,"level":3,"start":18090,"title":"麗春院詞二首"},{"anchor":"h3-西江月-85abfe","children":[],"end":18306,"level":3,"start":18234,"title":"西江月"},{"anchor":"h3-自題無根樹詞二首-ddbcc7","children":[{"anchor":"h4-鷓鴣天-89b2a4","children":[],"end":18397,"level":4,"start":18320,"title":"鷓鴣天"}],"end":18397,"level":3,"start":18306,"title":"自題無根樹詞二首"},{"anchor":"h3-賣花聲-4583e5","children":[],"end":18440,"level":3,"start":18397,"title":"賣花聲"},{"anchor":"h3-無根樹道情二十四首-753916","children":[{"anchor":"h4-又-73e1d4","children":[],"end":18733,"level":4,"start":18661,"title":"又"},{"anchor":"h4-又-73e1d4-2","children":[],"end":18806,"level":4,"start":18733,"title":"又"},{"anchor":"h4-又-73e1d4-3","children":[],"end":18878,"level":4,"start":18806,"title":"又"},{"anchor":"h4-又-73e1d4-4","children":[],"end":18950,"level":4,"start":18878,"title":"又"},{"anchor":"h4-又-73e1d4-5","children":[],"end":19022,"level":4,"start":18950,"title":"又"},{"anchor":"h4-又-73e1d4-6","children":[],"end":19094,"level":4,"start":19022,"title":"又"},{"anchor":"h4-又-73e1d4-7","children":[],"end":19166,"level":4,"start":19094,"title":"又"},{"anchor":"h4-又-73e1d4-8","children":[],"end":19238,"level":4,"start":19166,"title":"又"},{"anchor":"h4-又-73e1d4-9","children":[],"end":19310,"level":4,"start":19238,"title":"又"},{"anchor":"h4-又-73e1d4-10","children":[],"end":19382,"level":4,"start":19310,"title":"又"},{"anchor":"h4-又-73e1d4-11","children":[],"end":19454,"level":4,"start":19382,"title":"又"},{"anchor":"h4-又-73e1d4-12","children":[],"end":19526,"level":4,"start":19454,"title":"又"},{"anchor":"h4-又-73e1d4-13","children":[],"end":19598,"level":4,"start":19526,"title":"又"},{"anchor":"h4-又-73e1d4-14","children":[],"end":19670,"level":4,"start":19598,"title":"又"},{"anchor":"h4-又-73e1d4-15","children":[],"end":19742,"level":4,"start":19670,"title":"又"},{"anchor":"h4-又-73e1d4-16","children":[],"end":19814,"level":4,"start":19742,"title":"又"},{"anchor":"h4-又-73e1d4-17","children":[],"end":19886,"level":4,"start":19814,"title":"又"},{"anchor":"h4-又-73e1d4-18","children":[],"end":19958,"level":4,"start":19886,"title":"又"},{"anchor":"h4-又-73e1d4-19","children":[],"end":20030,"level":4,"start":19958,"title":"又"},{"anchor":"h4-又-73e1d4-20","children":[],"end":20102,"level":4,"start":20030,"title":"又"},{"anchor":"h4-又-73e1d4-21","children":[],"end":20174,"level":4,"start":20102,"title":"又"},{"anchor":"h4-又-73e1d4-22","children":[],"end":20246,"level":4,"start":20174,"title":"又"},{"anchor":"h4-又-73e1d4-23","children":[],"end":20319,"level":4,"start":20246,"title":"又"}],"end":20319,"level":3,"start":18440,"title":"無根樹道情二十四首"},{"anchor":"h3-四時道情-40c3a2","children":[],"end":20672,"level":3,"start":20319,"title":"四時道情"},{"anchor":"h3-青羊宮留題道情四首-5308a9","children":[{"anchor":"h4-又-364db8","children":[],"end":20947,"level":4,"start":20810,"title":"又"},{"anchor":"h4-又-364db8-2","children":[],"end":21068,"level":4,"start":20947,"title":"又"},{"anchor":"h4-又-364db8-3","children":[],"end":21192,"level":4,"start":21068,"title":"又"}],"end":21192,"level":3,"start":20672,"title":"青羊宮留題道情四首"},{"anchor":"h3-五更道情-6fd3c8","children":[{"anchor":"h4-又-d55f59","children":[],"end":21365,"level":4,"start":21280,"title":"又"},{"anchor":"h4-又-d55f59-2","children":[],"end":21451,"level":4,"start":21365,"title":"又"},{"anchor":"h4-又-d55f59-3","children":[],"end":21537,"level":4,"start":21451,"title":"又"},{"anchor":"h4-又-d55f59-4","children":[],"end":21623,"level":4,"start":21537,"title":"又"}],"end":21623,"level":3,"start":21192,"title":"五更道情"},{"anchor":"h3-五更道情-6fd3c8-2","children":[{"anchor":"h4-又-d55f59-5","children":[],"end":21841,"level":4,"start":21749,"title":"又"},{"anchor":"h4-又-d55f59-6","children":[],"end":21938,"level":4,"start":21841,"title":"又"},{"anchor":"h4-又-d55f59-7","children":[],"end":22044,"level":4,"start":21938,"title":"又"},{"anchor":"h4-又-d55f59-8","children":[],"end":22145,"level":4,"start":22044,"title":"又"}],"end":22145,"level":3,"start":21623,"title":"五更道情"},{"anchor":"h3-五更道情-6fd3c8-3","children":[{"anchor":"h4-又-d55f59-9","children":[],"end":22315,"level":4,"start":22231,"title":"又"},{"anchor":"h4-又-d55f59-10","children":[],"end":22399,"level":4,"start":22315,"title":"又"},{"anchor":"h4-又-d55f59-11","children":[],"end":22483,"level":4,"start":22399,"title":"又"},{"anchor":"h4-又-d55f59-12","children":[],"end":22567,"level":4,"start":22483,"title":"又"}],"end":22567,"level":3,"start":22145,"title":"五更道情"},{"anchor":"h3-五更道情-6fd3c8-4","children":[{"anchor":"h4-又-d55f59-13","children":[],"end":22852,"level":4,"start":22740,"title":"又"},{"anchor":"h4-又-d55f59-14","children":[],"end":22963,"level":4,"start":22852,"title":"又"},{"anchor":"h4-又-d55f59-15","children":[],"end":23072,"level":4,"start":22963,"title":"又"},{"anchor":"h4-又-d55f59-16","children":[],"end":23184,"level":4,"start":23072,"title":"又"}],"end":23184,"level":3,"start":22567,"title":"五更道情"},{"anchor":"h3-五更道情-6fd3c8-5","children":[{"anchor":"h4-又-d55f59-17","children":[],"end":23437,"level":4,"start":23329,"title":"又"},{"anchor":"h4-又-d55f59-18","children":[],"end":23545,"level":4,"start":23437,"title":"又"},{"anchor":"h4-又-d55f59-19","children":[],"end":23652,"level":4,"start":23545,"title":"又"},{"anchor":"h4-又-d55f59-20","children":[],"end":23760,"level":4,"start":23652,"title":"又"},{"anchor":"h4-又-d55f59-21","children":[],"end":23868,"level":4,"start":23760,"title":"又"},{"anchor":"h4-又-d55f59-22","children":[],"end":23976,"level":4,"start":23868,"title":"又"},{"anchor":"h4-又-d55f59-23","children":[],"end":24084,"level":4,"start":23976,"title":"又"},{"anchor":"h4-又-d55f59-24","children":[],"end":24192,"level":4,"start":24084,"title":"又"},{"anchor":"h4-又-d55f59-25","children":[],"end":24488,"level":4,"start":24192,"title":"又"}],"end":24488,"level":3,"start":23184,"title":"五更道情"},{"anchor":"h3-九更道情-2e091e","children":[{"anchor":"h4-又-9afbc2","children":[],"end":24674,"level":4,"start":24599,"title":"又"},{"anchor":"h4-又-9afbc2-2","children":[],"end":24749,"level":4,"start":24674,"title":"又"},{"anchor":"h4-又-9afbc2-3","children":[],"end":24823,"level":4,"start":24749,"title":"又"},{"anchor":"h4-又-9afbc2-4","children":[],"end":24899,"level":4,"start":24823,"title":"又"},{"anchor":"h4-又-9afbc2-5","children":[],"end":24975,"level":4,"start":24899,"title":"又"},{"anchor":"h4-又-9afbc2-6","children":[],"end":25050,"level":4,"start":24975,"title":"又"},{"anchor":"h4-又-9afbc2-7","children":[],"end":25125,"level":4,"start":25050,"title":"又"},{"anchor":"h4-又-9afbc2-8","children":[],"end":25200,"level":4,"start":25125,"title":"又"}],"end":25200,"level":3,"start":24488,"title":"九更道情"},{"anchor":"h3-嘆出家道情七首-bc3499","children":[{"anchor":"h4-又-fff9d0","children":[],"end":25414,"level":4,"start":25310,"title":"又"},{"anchor":"h4-又-fff9d0-2","children":[],"end":25496,"level":4,"start":25414,"title":"又"},{"anchor":"h4-又-fff9d0-3","children":[],"end":25577,"level":4,"start":25496,"title":"又"},{"anchor":"h4-又-fff9d0-4","children":[],"end":25681,"level":4,"start":25577,"title":"又"},{"anchor":"h4-又-fff9d0-5","children":[],"end":25882,"level":4,"start":25681,"title":"又"},{"anchor":"h4-又-fff9d0-6","children":[],"end":26063,"level":4,"start":25882,"title":"又"}],"end":26063,"level":3,"start":25200,"title":"嘆出家道情七首"},{"anchor":"h3-天邊月道情九首-5d9c6a","children":[{"anchor":"h4-又-c185f5","children":[],"end":26282,"level":4,"start":26173,"title":"又"},{"anchor":"h4-又-c185f5-2","children":[],"end":26386,"level":4,"start":26282,"title":"又"},{"anchor":"h4-又-c185f5-3","children":[],"end":26491,"level":4,"start":26386,"title":"又"},{"anchor":"h4-又-c185f5-4","children":[],"end":26596,"level":4,"start":26491,"title":"又"},{"anchor":"h4-又-c185f5-5","children":[],"end":26701,"level":4,"start":26596,"title":"又"},{"anchor":"h4-又-c185f5-6","children":[],"end":26805,"level":4,"start":26701,"title":"又"},{"anchor":"h4-又-c185f5-7","children":[],"end":26909,"level":4,"start":26805,"title":"又"},{"anchor":"h4-又-c185f5-8","children":[],"end":27013,"level":4,"start":26909,"title":"又"}],"end":27013,"level":3,"start":26063,"title":"天邊月道情九首"},{"anchor":"h3-一掃光道情十二首-e631ee","children":[{"anchor":"h4-又-0d169f","children":[],"end":27162,"level":4,"start":27090,"title":"又"},{"anchor":"h4-又-0d169f-2","children":[],"end":27234,"level":4,"start":27162,"title":"又"},{"anchor":"h4-又-0d169f-3","children":[],"end":27306,"level":4,"start":27234,"title":"又"},{"anchor":"h4-又-0d169f-4","children":[],"end":27378,"level":4,"start":27306,"title":"又"},{"anchor":"h4-又-0d169f-5","children":[],"end":27450,"level":4,"start":27378,"title":"又"},{"anchor":"h4-又-0d169f-6","children":[],"end":27521,"level":4,"start":27450,"title":"又"},{"anchor":"h4-又-0d169f-7","children":[],"end":27593,"level":4,"start":27521,"title":"又"},{"anchor":"h4-又-0d169f-8","children":[],"end":27665,"level":4,"start":27593,"title":"又"},{"anchor":"h4-又-0d169f-9","children":[],"end":27737,"level":4,"start":27665,"title":"又"},{"anchor":"h4-又-0d169f-10","children":[],"end":27809,"level":4,"start":27737,"title":"又"},{"anchor":"h4-又-0d169f-11","children":[],"end":27881,"level":4,"start":27809,"title":"又"}],"end":27881,"level":3,"start":27013,"title":"一掃光道情十二首"},{"anchor":"h3-鷓鵠天-3eba3e","children":[],"end":27955,"level":3,"start":27881,"title":"鷓鵠天"},{"anchor":"h3-五更道情-6fd3c8-6","children":[{"anchor":"h4-又-d55f59-26","children":[],"end":28101,"level":4,"start":28029,"title":"又"},{"anchor":"h4-又-d55f59-27","children":[],"end":28173,"level":4,"start":28101,"title":"又"},{"anchor":"h4-又-d55f59-28","children":[],"end":28245,"level":4,"start":28173,"title":"又"},{"anchor":"h4-又-d55f59-29","children":[],"end":28317,"level":4,"start":28245,"title":"又"}],"end":28317,"level":3,"start":27955,"title":"五更道情"},{"anchor":"h3-玄機問答-93395a","children":[],"end":28495,"level":3,"start":28317,"title":"玄機問答"}],"end":28495,"level":2,"start":13374,"title":"玄要篇下"}],"slug":"wikisource-張三丰先生全集-卷4"}