{"sections":[{"anchor":"h2-桓公元年-be34b0","children":[],"end":97,"level":2,"start":19,"title":"桓公元年"},{"anchor":"h2-桓公二年-5886ae","children":[],"end":585,"level":2,"start":97,"title":"桓公二年"},{"anchor":"h2-桓公三年-2d4497","children":[],"end":976,"level":2,"start":585,"title":"桓公三年"},{"anchor":"h2-桓公四年-c2fe0e","children":[],"end":1073,"level":2,"start":976,"title":"桓公四年"},{"anchor":"h2-桓公五年-f43439","children":[],"end":1345,"level":2,"start":1073,"title":"桓公五年"},{"anchor":"h2-桓公六年-129616","children":[],"end":1615,"level":2,"start":1345,"title":"桓公六年"},{"anchor":"h2-桓公七年-334854","children":[],"end":1715,"level":2,"start":1615,"title":"桓公七年"},{"anchor":"h2-桓公八年-7cee96","children":[],"end":1891,"level":2,"start":1715,"title":"桓公八年"},{"anchor":"h2-桓公九年-b83fb7","children":[],"end":2040,"level":2,"start":1891,"title":"桓公九年"},{"anchor":"h2-桓公十年-7e90cb","children":[],"end":2193,"level":2,"start":2040,"title":"桓公十年"},{"anchor":"h2-桓公十一年-bb61ab","children":[],"end":2417,"level":2,"start":2193,"title":"桓公十一年"},{"anchor":"h2-桓公十二年-bde64f","children":[],"end":2608,"level":2,"start":2417,"title":"桓公十二年"},{"anchor":"h2-桓公十三年-1187b9","children":[],"end":2744,"level":2,"start":2608,"title":"桓公十三年"},{"anchor":"h2-桓公十四年-9c54a7","children":[],"end":3133,"level":2,"start":2744,"title":"桓公十四年"},{"anchor":"h2-桓公十五年-43b8e1","children":[],"end":3376,"level":2,"start":3133,"title":"桓公十五年"},{"anchor":"h2-桓公十六年-f726d2","children":[],"end":3495,"level":2,"start":3376,"title":"桓公十六年"},{"anchor":"h2-桓公十七年-861f98","children":[],"end":3684,"level":2,"start":3495,"title":"桓公十七年"},{"anchor":"h2-桓公十八年-882575","children":[],"end":3919,"level":2,"start":3684,"title":"桓公十八年"}],"slug":"wikisource-春秋穀梁傳-桓公"}