{"sections":[{"anchor":"h2-裴君-d04aa8","children":[],"end":1116,"level":2,"start":0,"title":"裴君"},{"anchor":"h2-樂巴-2dbb94","children":[],"end":2157,"level":2,"start":1116,"title":"樂巴"},{"anchor":"h2-左慈-0ae67a","children":[],"end":3688,"level":2,"start":2157,"title":"左慈"},{"anchor":"h2-孔元方-8ffa39","children":[],"end":4194,"level":2,"start":3688,"title":"孔元方"},{"anchor":"h2-焦先-5a9699","children":[],"end":4600,"level":2,"start":4194,"title":"焦先"},{"anchor":"h2-陽翁伯-a60ea0","children":[],"end":4781,"level":2,"start":4600,"title":"陽翁伯"},{"anchor":"h2-李意期-679654","children":[],"end":5050,"level":2,"start":4781,"title":"李意期"},{"anchor":"h2-杜契-2b1f37","children":[],"end":5206,"level":2,"start":5050,"title":"杜契"},{"anchor":"h2-李阿-3e13b4","children":[],"end":5643,"level":2,"start":5206,"title":"李阿"},{"anchor":"h2-介象-6d76de","children":[],"end":6759,"level":2,"start":5643,"title":"介象"}],"slug":"wikisource-歷世真仙體道通鑑-15"}